mcu_geo_utils/OSM.py
mcu_geo_utils/__init__.py
mcu_geo_utils/census.py
mcu_geo_utils-0.6.dist-info/LICENSE
mcu_geo_utils-0.6.dist-info/METADATA
mcu_geo_utils-0.6.dist-info/WHEEL
mcu_geo_utils-0.6.dist-info/top_level.txt
mcu_geo_utils-0.6.dist-info/RECORD
