Metadata-Version: 2.1
Name: mcu-geo-utils
Version: 0.6
Summary: variaty of geo-related tools
Home-page: https://pypi.org/project/mcu-geo-utils/
Author: Martin Conur
Author-email: martincontrerasur@gmail.com
License: MIT
License-File: LICENSE
Requires-Dist: pandas (>=1.0)
Requires-Dist: geopandas (>=0.12.0)
Requires-Dist: shapely (==2.0.1)
Requires-Dist: osmnx (==1.5.1)
